tap_CHANGEME
tap_wootric
