Metadata-Version: 1.1
Name: tap-wootric
Version: 0.4.3
Summary: Singer.io tap for extracting data from the Wootric API
Home-page: http://singer.io
Author: Stitch
Author-email: UNKNOWN
License: UNKNOWN
Platform: UNKNOWN
Classifier: Programming Language :: Python :: 3 :: Only
